{
  "Tables": {
    "START": {
      "SubTables": {
        "203": "BITS",
        "221": "IX",
        "237": "ED",
        "253": "IY"
      },
      "Opcodes": {
        "0": "nop",
        "1": "ld bc,**",
        "2": "ld (bc),a",
        "3": "inc bc",
        "4": "inc b",
        "5": "dec b",
        "6": "ld b,*",
        "7": "rlca",
        "8": "ex af,af'",
        "9": "add hl,bc",
        "10": "ld a,(bc)",
        "11": "dec bc",
        "12": "inc c",
        "13": "dec c",
        "14": "ld c,*",
        "15": "rrca",
        "16": "djnz +*",
        "17": "ld de,**",
        "18": "ld (de),a",
        "19": "inc de",
        "20": "inc d",
        "21": "dec d",
        "22": "ld d,*",
        "23": "rla",
        "24": "jr +*",
        "25": "add hl,de",
        "26": "ld a,(de)",
        "27": "dec de",
        "28": "inc e",
        "29": "dec e",
        "30": "ld e,*",
        "31": "rra",
        "32": "jr nz,+*",
        "33": "ld hl,**",
        "34": "ld (**),hl",
        "35": "inc hl",
        "36": "inc h",
        "37": "dec h",
        "38": "ld h,*",
        "39": "daa",
        "40": "jr z,+*",
        "41": "add hl,hl",
        "42": "ld hl,(**)",
        "43": "dec hl",
        "44": "inc l",
        "45": "dec l",
        "46": "ld l,*",
        "47": "cpl",
        "48": "jr nc,+*",
        "49": "ld sp,**",
        "50": "ld (**),a",
        "51": "inc sp",
        "52": "inc (hl)",
        "53": "dec (hl)",
        "54": "ld (hl),*",
        "55": "scf",
        "56": "jr c,+*",
        "57": "add hl,sp",
        "58": "ld a,(**)",
        "59": "dec sp",
        "60": "inc a",
        "61": "dec a",
        "62": "ld a,*",
        "63": "ccf",
        "64": "ld b,b",
        "65": "ld b,c",
        "66": "ld b,d",
        "67": "ld b,e",
        "68": "ld b,h",
        "69": "ld b,l",
        "70": "ld b,(hl)",
        "71": "ld b,a",
        "72": "ld c,b",
        "73": "ld c,c",
        "74": "ld c,d",
        "75": "ld c,e",
        "76": "ld c,h",
        "77": "ld c,l",
        "78": "ld c,(hl)",
        "79": "ld c,a",
        "80": "ld d,b",
        "81": "ld d,c",
        "82": "ld d,d",
        "83": "ld d,e",
        "84": "ld d,h",
        "85": "ld d,l",
        "86": "ld d,(hl)",
        "87": "ld d,a",
        "88": "ld e,b",
        "89": "ld e,c",
        "90": "ld e,d",
        "91": "ld e,e",
        "92": "ld e,h",
        "93": "ld e,l",
        "94": "ld e,(hl)",
        "95": "ld e,a",
        "96": "ld h,b",
        "97": "ld h,c",
        "98": "ld h,d",
        "99": "ld h,e",
        "100": "ld h,h",
        "101": "ld h,l",
        "102": "ld h,(hl)",
        "103": "ld h,a",
        "104": "ld l,b",
        "105": "ld l,c",
        "106": "ld l,d",
        "107": "ld l,e",
        "108": "ld l,h",
        "109": "ld l,l",
        "110": "ld l,(hl)",
        "111": "ld l,a",
        "112": "ld (hl),b",
        "113": "ld (hl),c",
        "114": "ld (hl),d",
        "115": "ld (hl),e",
        "116": "ld (hl),h",
        "117": "ld (hl),l",
        "118": "halt",
        "119": "ld (hl),a",
        "120": "ld a,b",
        "121": "ld a,c",
        "122": "ld a,d",
        "123": "ld a,e",
        "124": "ld a,h",
        "125": "ld a,l",
        "126": "ld a,(hl)",
        "127": "ld a,a",
        "128": "add a,b",
        "129": "add a,c",
        "130": "add a,d",
        "131": "add a,e",
        "132": "add a,h",
        "133": "add a,l",
        "134": "add a,(hl)",
        "135": "add a,a",
        "136": "adc a,b",
        "137": "adc a,c",
        "138": "adc a,d",
        "139": "adc a,e",
        "140": "adc a,h",
        "141": "adc a,l",
        "142": "adc a,(hl)",
        "143": "adc a,a",
        "144": "sub b",
        "145": "sub c",
        "146": "sub d",
        "147": "sub e",
        "148": "sub h",
        "149": "sub l",
        "150": "sub (hl)",
        "151": "sub a",
        "152": "sbc a,b",
        "153": "sbc a,c",
        "154": "sbc a,d",
        "155": "sbc a,e",
        "156": "sbc a,h",
        "157": "sbc a,l",
        "158": "sbc a,(hl)",
        "159": "sbc a,a",
        "160": "and b",
        "161": "and c",
        "162": "and d",
        "163": "and e",
        "164": "and h",
        "165": "and l",
        "166": "and (hl)",
        "167": "and a",
        "168": "xor b",
        "169": "xor c",
        "170": "xor d",
        "171": "xor e",
        "172": "xor h",
        "173": "xor l",
        "174": "xor (hl)",
        "175": "xor a",
        "176": "or b",
        "177": "or c",
        "178": "or d",
        "179": "or e",
        "180": "or h",
        "181": "or l",
        "182": "or (hl)",
        "183": "or a",
        "184": "cp b",
        "185": "cp c",
        "186": "cp d",
        "187": "cp e",
        "188": "cp h",
        "189": "cp l",
        "190": "cp (hl)",
        "191": "cp a",
        "192": "ret nz",
        "193": "pop bc",
        "194": "jp nz,**",
        "195": "jp **",
        "196": "call nz,**",
        "197": "push bc",
        "198": "add a,*",
        "199": "rst 00h",
        "200": "ret z",
        "201": "ret",
        "202": "jp z,**",
        "204": "call z,**",
        "205": "call **",
        "206": "adc a,*",
        "207": "rst 08h",
        "208": "ret nc",
        "209": "pop de",
        "210": "jp nc,**",
        "211": "out (*),a",
        "212": "call nc,**",
        "213": "push de",
        "214": "sub *",
        "215": "rst 10h",
        "216": "ret c",
        "217": "exx",
        "218": "jp c,**",
        "219": "in a,(*)",
        "220": "call c,**",
        "222": "sbc a,*",
        "223": "rst 18h",
        "224": "ret po",
        "225": "pop hl",
        "226": "jp po,**",
        "227": "ex (sp),hl",
        "228": "call po,**",
        "229": "push hl",
        "230": "and *",
        "231": "rst 20h",
        "232": "ret pe",
        "233": "jp (hl)",
        "234": "jp pe,**",
        "235": "ex de,hl",
        "236": "call pe,**",
        "238": "xor *",
        "239": "rst 28h",
        "240": "ret p",
        "241": "pop af",
        "242": "jp p,**",
        "243": "di",
        "244": "call p,**",
        "245": "push af",
        "246": "or *",
        "247": "rst 30h",
        "248": "ret m",
        "249": "ld sp,hl",
        "250": "jp m,**",
        "251": "ei",
        "252": "call m,**",
        "254": "cp *",
        "255": "rst 38h"
      }
    },
    "BITS": {
      "SubTables": {},
      "Opcodes": {
        "0": "rlc b",
        "1": "rlc c",
        "2": "rlc d",
        "3": "rlc e",
        "4": "rlc h",
        "5": "rlc l",
        "6": "rlc (hl)",
        "7": "rlc a",
        "8": "rrc b",
        "9": "rrc c",
        "10": "rrc d",
        "11": "rrc e",
        "12": "rrc h",
        "13": "rrc l",
        "14": "rrc (hl)",
        "15": "rrc a",
        "16": "rl b",
        "17": "rl c",
        "18": "rl d",
        "19": "rl e",
        "20": "rl h",
        "21": "rl l",
        "22": "rl (hl)",
        "23": "rl a",
        "24": "rr b",
        "25": "rr c",
        "26": "rr d",
        "27": "rr e",
        "28": "rr h",
        "29": "rr l",
        "30": "rr (hl)",
        "31": "rr a",
        "32": "sla b",
        "33": "sla c",
        "34": "sla d",
        "35": "sla e",
        "36": "sla h",
        "37": "sla l",
        "38": "sla (hl)",
        "39": "sla a",
        "40": "sra b",
        "41": "sra c",
        "42": "sra d",
        "43": "sra e",
        "44": "sra h",
        "45": "sra l",
        "46": "sra (hl)",
        "47": "sra a",
        "48": "sll b",
        "49": "sll c",
        "50": "sll d",
        "51": "sll e",
        "52": "sll h",
        "53": "sll l",
        "54": "sll (hl)",
        "55": "sll a",
        "56": "srl b",
        "57": "srl c",
        "58": "srl d",
        "59": "srl e",
        "60": "srl h",
        "61": "srl l",
        "62": "srl (hl)",
        "63": "srl a",
        "64": "bit 0,b",
        "65": "bit 0,c",
        "66": "bit 0,d",
        "67": "bit 0,e",
        "68": "bit 0,h",
        "69": "bit 0,l",
        "70": "bit 0,(hl)",
        "71": "bit 0,a",
        "72": "bit 1,b",
        "73": "bit 1,c",
        "74": "bit 1,d",
        "75": "bit 1,e",
        "76": "bit 1,h",
        "77": "bit 1,l",
        "78": "bit 1,(hl)",
        "79": "bit 1,a",
        "80": "bit 2,b",
        "81": "bit 2,c",
        "82": "bit 2,d",
        "83": "bit 2,e",
        "84": "bit 2,h",
        "85": "bit 2,l",
        "86": "bit 2,(hl)",
        "87": "bit 2,a",
        "88": "bit 3,b",
        "89": "bit 3,c",
        "90": "bit 3,d",
        "91": "bit 3,e",
        "92": "bit 3,h",
        "93": "bit 3,l",
        "94": "bit 3,(hl)",
        "95": "bit 3,a",
        "96": "bit 4,b",
        "97": "bit 4,c",
        "98": "bit 4,d",
        "99": "bit 4,e",
        "100": "bit 4,h",
        "101": "bit 4,l",
        "102": "bit 4,(hl)",
        "103": "bit 4,a",
        "104": "bit 5,b",
        "105": "bit 5,c",
        "106": "bit 5,d",
        "107": "bit 5,e",
        "108": "bit 5,h",
        "109": "bit 5,l",
        "110": "bit 5,(hl)",
        "111": "bit 5,a",
        "112": "bit 6,b",
        "113": "bit 6,c",
        "114": "bit 6,d",
        "115": "bit 6,e",
        "116": "bit 6,h",
        "117": "bit 6,l",
        "118": "bit 6,(hl)",
        "119": "bit 6,a",
        "120": "bit 7,b",
        "121": "bit 7,c",
        "122": "bit 7,d",
        "123": "bit 7,e",
        "124": "bit 7,h",
        "125": "bit 7,l",
        "126": "bit 7,(hl)",
        "127": "bit 7,a",
        "128": "res 0,b",
        "129": "res 0,c",
        "130": "res 0,d",
        "131": "res 0,e",
        "132": "res 0,h",
        "133": "res 0,l",
        "134": "res 0,(hl)",
        "135": "res 0,a",
        "136": "res 1,b",
        "137": "res 1,c",
        "138": "res 1,d",
        "139": "res 1,e",
        "140": "res 1,h",
        "141": "res 1,l",
        "142": "res 1,(hl)",
        "143": "res 1,a",
        "144": "res 2,b",
        "145": "res 2,c",
        "146": "res 2,d",
        "147": "res 2,e",
        "148": "res 2,h",
        "149": "res 2,l",
        "150": "res 2,(hl)",
        "151": "res 2,a",
        "152": "res 3,b",
        "153": "res 3,c",
        "154": "res 3,d",
        "155": "res 3,e",
        "156": "res 3,h",
        "157": "res 3,l",
        "158": "res 3,(hl)",
        "159": "res 3,a",
        "160": "res 4,b",
        "161": "res 4,c",
        "162": "res 4,d",
        "163": "res 4,e",
        "164": "res 4,h",
        "165": "res 4,l",
        "166": "res 4,(hl)",
        "167": "res 4,a",
        "168": "res 5,b",
        "169": "res 5,c",
        "170": "res 5,d",
        "171": "res 5,e",
        "172": "res 5,h",
        "173": "res 5,l",
        "174": "res 5,(hl)",
        "175": "res 5,a",
        "176": "res 6,b",
        "177": "res 6,c",
        "178": "res 6,d",
        "179": "res 6,e",
        "180": "res 6,h",
        "181": "res 6,l",
        "182": "res 6,(hl)",
        "183": "res 6,a",
        "184": "res 7,b",
        "185": "res 7,c",
        "186": "res 7,d",
        "187": "res 7,e",
        "188": "res 7,h",
        "189": "res 7,l",
        "190": "res 7,(hl)",
        "191": "res 7,a",
        "192": "set 0,b",
        "193": "set 0,c",
        "194": "set 0,d",
        "195": "set 0,e",
        "196": "set 0,h",
        "197": "set 0,l",
        "198": "set 0,(hl)",
        "199": "set 0,a",
        "200": "set 1,b",
        "201": "set 1,c",
        "202": "set 1,d",
        "203": "set 1,e",
        "204": "set 1,h",
        "205": "set 1,l",
        "206": "set 1,(hl)",
        "207": "set 1,a",
        "208": "set 2,b",
        "209": "set 2,c",
        "210": "set 2,d",
        "211": "set 2,e",
        "212": "set 2,h",
        "213": "set 2,l",
        "214": "set 2,(hl)",
        "215": "set 2,a",
        "216": "set 3,b",
        "217": "set 3,c",
        "218": "set 3,d",
        "219": "set 3,e",
        "220": "set 3,h",
        "221": "set 3,l",
        "222": "set 3,(hl)",
        "223": "set 3,a",
        "224": "set 4,b",
        "225": "set 4,c",
        "226": "set 4,d",
        "227": "set 4,e",
        "228": "set 4,h",
        "229": "set 4,l",
        "230": "set 4,(hl)",
        "231": "set 4,a",
        "232": "set 5,b",
        "233": "set 5,c",
        "234": "set 5,d",
        "235": "set 5,e",
        "236": "set 5,h",
        "237": "set 5,l",
        "238": "set 5,(hl)",
        "239": "set 5,a",
        "240": "set 6,b",
        "241": "set 6,c",
        "242": "set 6,d",
        "243": "set 6,e",
        "244": "set 6,h",
        "245": "set 6,l",
        "246": "set 6,(hl)",
        "247": "set 6,a",
        "248": "set 7,b",
        "249": "set 7,c",
        "250": "set 7,d",
        "251": "set 7,e",
        "252": "set 7,h",
        "253": "set 7,l",
        "254": "set 7,(hl)",
        "255": "set 7,a"
      }
    },
    "IX": {
      "SubTables": {
        "203": "IXBITS *"
      },
      "Opcodes": {
        "9": "add ix,bc",
        "25": "add ix,de",
        "33": "ld ix,**",
        "34": "ld (**),ix",
        "35": "inc ix",
        "36": "inc ixh",
        "37": "dec ixh",
        "38": "ld ixh,*",
        "41": "add ix,ix",
        "42": "ld ix,(**)",
        "43": "dec ix",
        "44": "inc ixl",
        "45": "dec ixl",
        "46": "ld ixl,*",
        "52": "inc (ix+*)",
        "53": "dec (ix+*)",
        "54": "ld (ix+*),*",
        "57": "add ix,sp",
        "68": "ld b,ixh",
        "69": "ld b,ixl",
        "70": "ld b,(ix+*)",
        "76": "ld c,ixh",
        "77": "ld c,ixl",
        "78": "ld c,(ix+*)",
        "84": "ld d,ixh",
        "85": "ld d,ixl",
        "86": "ld d,(ix+*)",
        "92": "ld e,ixh",
        "93": "ld e,ixl",
        "94": "ld e,(ix+*)",
        "96": "ld ixh,b",
        "97": "ld ixh,c",
        "98": "ld ixh,d",
        "99": "ld ixh,e",
        "100": "ld ixh,ixh",
        "101": "ld ixh,ixl",
        "102": "ld h,(ix+*)",
        "103": "ld ixh,a",
        "104": "ld ixl,b",
        "105": "ld ixl,c",
        "106": "ld ixl,d",
        "107": "ld ixl, e",
        "108": "ld ixl,ixh",
        "109": "ld ixl,ixl",
        "110": "ld l,(ix+*)",
        "111": "ld ixl,a",
        "112": "ld (ix+*),b",
        "113": "ld (ix+*),c",
        "114": "ld (ix+*),d",
        "115": "ld (ix+*),e",
        "116": "ld (ix+*),h",
        "117": "ld (ix+*),l",
        "119": "ld (ix+*),a",
        "124": "ld a,ixh",
        "125": "ld a,ixl",
        "126": "ld a,(ix+*)",
        "132": "add a,ixh",
        "133": "add a,ixl",
        "134": "add a,(ix+*)",
        "140": "adc a,ixh",
        "141": "adc a,ixl",
        "142": "adc a,(ix+*)",
        "148": "sub ixh",
        "149": "sub ixl",
        "150": "sub (ix+*)",
        "156": "sbc a,ixh",
        "157": "sbc a,ixl",
        "158": "sbc a,(ix+*)",
        "164": "and ixh",
        "165": "and ixl",
        "166": "and (ix+*)",
        "172": "xor ixh",
        "173": "xor ixl",
        "174": "xor (ix+*)",
        "180": "or ixh",
        "181": "or ixl",
        "182": "or (ix+*)",
        "188": "cp ixh",
        "189": "cp ixl",
        "190": "cp (ix+*)",
        "225": "pop ix",
        "227": "ex (sp),ix",
        "229": "push ix",
        "233": "jp (ix)",
        "249": "ld sp,ix"
      }
    },
    "IXBITS": {
      "SubTables": {},
      "Opcodes": {
        "0": "rlc (ix+*),b",
        "1": "rlc (ix+*),c",
        "2": "rlc (ix+*),d",
        "3": "rlc (ix+*),e",
        "4": "rlc (ix+*),h",
        "5": "rlc (ix+*),l",
        "6": "rlc (ix+*)",
        "7": "rlc (ix+*),a",
        "8": "rrc (ix+*),b",
        "9": "rrc (ix+*),c",
        "10": "rrc (ix+*),d",
        "11": "rrc (ix+*),e",
        "12": "rrc (ix+*),h",
        "13": "rrc (ix+*),l",
        "14": "rrc (ix+*)",
        "15": "rrc (ix+*),a",
        "16": "rl (ix+*),b",
        "17": "rl (ix+*),c",
        "18": "rl (ix+*),d",
        "19": "rl (ix+*),e",
        "20": "rl (ix+*),h",
        "21": "rl (ix+*),l",
        "22": "rl (ix+*)",
        "23": "rl (ix+*),a",
        "24": "rr (ix+*),b",
        "25": "rr (ix+*),c",
        "26": "rr (ix+*),d",
        "27": "rr (ix+*),e",
        "28": "rr (ix+*),h",
        "29": "rr (ix+*),l",
        "30": "rr (ix+*)",
        "31": "rr (ix+*),a",
        "32": "sla (ix+*),b",
        "33": "sla (ix+*),c",
        "34": "sla (ix+*),d",
        "35": "sla (ix+*),e",
        "36": "sla (ix+*),h",
        "37": "sla (ix+*),l",
        "38": "sla (ix+*)",
        "39": "sla (ix+*),a",
        "40": "sra (ix+*),b",
        "41": "sra (ix+*),c",
        "42": "sra (ix+*),d",
        "43": "sra (ix+*),e",
        "44": "sra (ix+*),h",
        "45": "sra (ix+*),l",
        "46": "sra (ix+*)",
        "47": "sra (ix+*),a",
        "48": "sll (ix+*),b",
        "49": "sll (ix+*),c",
        "50": "sll (ix+*),d",
        "51": "sll (ix+*),e",
        "52": "sll (ix+*),h",
        "53": "sll (ix+*),l",
        "54": "sll (ix+*)",
        "55": "sll (ix+*),a",
        "56": "srl (ix+*),b",
        "57": "srl (ix+*),c",
        "58": "srl (ix+*),d",
        "59": "srl (ix+*),e",
        "60": "srl (ix+*),h",
        "61": "srl (ix+*),l",
        "62": "srl (ix+*)",
        "63": "srl (ix+*),a",
        "64": "bit 0,(ix+*)",
        "65": "bit 0,(ix+*)",
        "66": "bit 0,(ix+*)",
        "67": "bit 0,(ix+*)",
        "68": "bit 0,(ix+*)",
        "69": "bit 0,(ix+*)",
        "70": "bit 0,(ix+*)",
        "71": "bit 0,(ix+*)",
        "72": "bit 1,(ix+*)",
        "73": "bit 1,(ix+*)",
        "74": "bit 1,(ix+*)",
        "75": "bit 1,(ix+*)",
        "76": "bit 1,(ix+*)",
        "77": "bit 1,(ix+*)",
        "78": "bit 1,(ix+*)",
        "79": "bit 1,(ix+*)",
        "80": "bit 2,(ix+*)",
        "81": "bit 2,(ix+*)",
        "82": "bit 2,(ix+*)",
        "83": "bit 2,(ix+*)",
        "84": "bit 2,(ix+*)",
        "85": "bit 2,(ix+*)",
        "86": "bit 2,(ix+*)",
        "87": "bit 2,(ix+*)",
        "88": "bit 3,(ix+*)",
        "89": "bit 3,(ix+*)",
        "90": "bit 3,(ix+*)",
        "91": "bit 3,(ix+*)",
        "92": "bit 3,(ix+*)",
        "93": "bit 3,(ix+*)",
        "94": "bit 3,(ix+*)",
        "95": "bit 3,(ix+*)",
        "96": "bit 4,(ix+*)",
        "97": "bit 4,(ix+*)",
        "98": "bit 4,(ix+*)",
        "99": "bit 4,(ix+*)",
        "100": "bit 4,(ix+*)",
        "101": "bit 4,(ix+*)",
        "102": "bit 4,(ix+*)",
        "103": "bit 4,(ix+*)",
        "104": "bit 5,(ix+*)",
        "105": "bit 5,(ix+*)",
        "106": "bit 5,(ix+*)",
        "107": "bit 5,(ix+*)",
        "108": "bit 5,(ix+*)",
        "109": "bit 5,(ix+*)",
        "110": "bit 5,(ix+*)",
        "111": "bit 5,(ix+*)",
        "112": "bit 6,(ix+*)",
        "113": "bit 6,(ix+*)",
        "114": "bit 6,(ix+*)",
        "115": "bit 6,(ix+*)",
        "116": "bit 6,(ix+*)",
        "117": "bit 6,(ix+*)",
        "118": "bit 6,(ix+*)",
        "119": "bit 6,(ix+*)",
        "120": "bit 7,(ix+*)",
        "121": "bit 7,(ix+*)",
        "122": "bit 7,(ix+*)",
        "123": "bit 7,(ix+*)",
        "124": "bit 7,(ix+*)",
        "125": "bit 7,(ix+*)",
        "126": "bit 7,(ix+*)",
        "127": "bit 7,(ix+*)",
        "128": "res 0,(ix+*),b",
        "129": "res 0,(ix+*),c",
        "130": "res 0,(ix+*),d",
        "131": "res 0,(ix+*),e",
        "132": "res 0,(ix+*),h",
        "133": "res 0,(ix+*),l",
        "134": "res 0,(ix+*)",
        "135": "res 0,(ix+*),a",
        "136": "res 1,(ix+*),b",
        "137": "res 1,(ix+*),c",
        "138": "res 1,(ix+*),d",
        "139": "res 1,(ix+*),e",
        "140": "res 1,(ix+*),h",
        "141": "res 1,(ix+*),l",
        "142": "res 1,(ix+*)",
        "143": "res 1,(ix+*),a",
        "144": "res 2,(ix+*),b",
        "145": "res 2,(ix+*),c",
        "146": "res 2,(ix+*),d",
        "147": "res 2,(ix+*),e",
        "148": "res 2,(ix+*),h",
        "149": "res 2,(ix+*),l",
        "150": "res 2,(ix+*)",
        "151": "res 2,(ix+*),a",
        "152": "res 3,(ix+*),b",
        "153": "res 3,(ix+*),c",
        "154": "res 3,(ix+*),d",
        "155": "res 3,(ix+*),e",
        "156": "res 3,(ix+*),h",
        "157": "res 3,(ix+*),l",
        "158": "res 3,(ix+*)",
        "159": "res 3,(ix+*),a",
        "160": "res 4,(ix+*),b",
        "161": "res 4,(ix+*),c",
        "162": "res 4,(ix+*),d",
        "163": "res 4,(ix+*),e",
        "164": "res 4,(ix+*),h",
        "165": "res 4,(ix+*),l",
        "166": "res 4,(ix+*)",
        "167": "res 4,(ix+*),a",
        "168": "res 5,(ix+*),b",
        "169": "res 5,(ix+*),c",
        "170": "res 5,(ix+*),d",
        "171": "res 5,(ix+*),e",
        "172": "res 5,(ix+*),h",
        "173": "res 5,(ix+*),l",
        "174": "res 5,(ix+*)",
        "175": "res 5,(ix+*),a",
        "176": "res 6,(ix+*),b",
        "177": "res 6,(ix+*),c",
        "178": "res 6,(ix+*),d",
        "179": "res 6,(ix+*),e",
        "180": "res 6,(ix+*),h",
        "181": "res 6,(ix+*),l",
        "182": "res 6,(ix+*)",
        "183": "res 6,(ix+*),a",
        "184": "res 7,(ix+*),b",
        "185": "res 7,(ix+*),c",
        "186": "res 7,(ix+*),d",
        "187": "res 7,(ix+*),e",
        "188": "res 7,(ix+*),h",
        "189": "res 7,(ix+*),l",
        "190": "res 7,(ix+*)",
        "191": "res 7,(ix+*),a",
        "192": "set 0,(ix+*),b",
        "193": "set 0,(ix+*),c",
        "194": "set 0,(ix+*),d",
        "195": "set 0,(ix+*),e",
        "196": "set 0,(ix+*),h",
        "197": "set 0,(ix+*),l",
        "198": "set 0,(ix+*)",
        "199": "set 0,(ix+*),a",
        "200": "set 1,(ix+*),b",
        "201": "set 1,(ix+*),c",
        "202": "set 1,(ix+*),d",
        "203": "set 1,(ix+*),e",
        "204": "set 1,(ix+*),h",
        "205": "set 1,(ix+*),l",
        "206": "set 1,(ix+*)",
        "207": "set 1,(ix+*),a",
        "208": "set 2,(ix+*),b",
        "209": "set 2,(ix+*),c",
        "210": "set 2,(ix+*),d",
        "211": "set 2,(ix+*),e",
        "212": "set 2,(ix+*),h",
        "213": "set 2,(ix+*),l",
        "214": "set 2,(ix+*)",
        "215": "set 2,(ix+*),a",
        "216": "set 3,(ix+*),b",
        "217": "set 3,(ix+*),c",
        "218": "set 3,(ix+*),d",
        "219": "set 3,(ix+*),e",
        "220": "set 3,(ix+*),h",
        "221": "set 3,(ix+*),l",
        "222": "set 3,(ix+*)",
        "223": "set 3,(ix+*),a",
        "224": "set 4,(ix+*),b",
        "225": "set 4,(ix+*),c",
        "226": "set 4,(ix+*),d",
        "227": "set 4,(ix+*),e",
        "228": "set 4,(ix+*),h",
        "229": "set 4,(ix+*),l",
        "230": "set 4,(ix+*)",
        "231": "set 4,(ix+*),a",
        "232": "set 5,(ix+*),b",
        "233": "set 5,(ix+*),c",
        "234": "set 5,(ix+*),d",
        "235": "set 5,(ix+*),e",
        "236": "set 5,(ix+*),h",
        "237": "set 5,(ix+*),l",
        "238": "set 5,(ix+*)",
        "239": "set 5,(ix+*),a",
        "240": "set 6,(ix+*),b",
        "241": "set 6,(ix+*),c",
        "242": "set 6,(ix+*),d",
        "243": "set 6,(ix+*),e",
        "244": "set 6,(ix+*),h",
        "245": "set 6,(ix+*),l",
        "246": "set 6,(ix+*)",
        "247": "set 6,(ix+*),a",
        "248": "set 7,(ix+*),b",
        "249": "set 7,(ix+*),c",
        "250": "set 7,(ix+*),d",
        "251": "set 7,(ix+*),e",
        "252": "set 7,(ix+*),h",
        "253": "set 7,(ix+*),l",
        "254": "set 7,(ix+*)",
        "255": "set 7,(ix+*),a"
      }
    },
    "IY": {
      "SubTables": {
        "203": "IYBITS *"
      },
      "Opcodes": {
        "9": "add iy,bc",
        "25": "add iy,de",
        "33": "ld iy,**",
        "34": "ld (**),iy",
        "35": "inc iy",
        "36": "inc iyh",
        "37": "dec iyh",
        "38": "ld iyh,*",
        "41": "add iy,iy",
        "42": "ld iy,(**)",
        "43": "dec iy",
        "44": "inc iyl",
        "45": "dec iyl",
        "46": "ld iyl,*",
        "52": "inc (iy+*)",
        "53": "dec (iy+*)",
        "54": "ld (iy+*),*",
        "57": "add iy,sp",
        "68": "ld b,iyh",
        "69": "ld b,iyl",
        "70": "ld b,(iy+*)",
        "76": "ld c,iyh",
        "77": "ld c,iyl",
        "78": "ld c,(iy+*)",
        "84": "ld d,iyh",
        "85": "ld d,iyl",
        "86": "ld d,(iy+*)",
        "92": "ld e,iyh",
        "93": "ld e,iyl",
        "94": "ld e,(iy+*)",
        "96": "ld iyh,b",
        "97": "ld iyh,c",
        "98": "ld iyh,d",
        "99": "ld iyh,e",
        "100": "ld iyh,iyh",
        "101": "ld iyh,iyl",
        "102": "ld h,(iy+*)",
        "103": "ld iyh,a",
        "104": "ld iyl,b",
        "105": "ld iyl,c",
        "106": "ld iyl,d",
        "107": "ld iyl, e",
        "108": "ld iyl,iyh",
        "109": "ld iyl,iyl",
        "110": "ld l,(iy+*)",
        "111": "ld iyl,a",
        "112": "ld (iy+*),b",
        "113": "ld (iy+*),c",
        "114": "ld (iy+*),d",
        "115": "ld (iy+*),e",
        "116": "ld (iy+*),h",
        "117": "ld (iy+*),l",
        "119": "ld (iy+*),a",
        "124": "ld a,iyh",
        "125": "ld a,iyl",
        "126": "ld a,(iy+*)",
        "132": "add a,iyh",
        "133": "add a,iyl",
        "134": "add a,(iy+*)",
        "140": "adc a,iyh",
        "141": "adc a,iyl",
        "142": "adc a,(iy+*)",
        "148": "sub iyh",
        "149": "sub iyl",
        "150": "sub (iy+*)",
        "156": "sbc a,iyh",
        "157": "sbc a,iyl",
        "158": "sbc a,(iy+*)",
        "164": "and iyh",
        "165": "and iyl",
        "166": "and (iy+*)",
        "172": "xor iyh",
        "173": "xor iyl",
        "174": "xor (iy+*)",
        "180": "or iyh",
        "181": "or iyl",
        "182": "or (iy+*)",
        "188": "cp iyh",
        "189": "cp iyl",
        "190": "cp (iy+*)",
        "225": "pop iy",
        "227": "ex (sp),iy",
        "229": "push iy",
        "233": "jp (iy)",
        "249": "ld sp,iy"
      }
    },
    "IYBITS": {
      "SubTables": {},
      "Opcodes": {
        "0": "rlc (iy+*),b",
        "1": "rlc (iy+*),c",
        "2": "rlc (iy+*),d",
        "3": "rlc (iy+*),e",
        "4": "rlc (iy+*),h",
        "5": "rlc (iy+*),l",
        "6": "rlc (iy+*)",
        "7": "rlc (iy+*),a",
        "8": "rrc (iy+*),b",
        "9": "rrc (iy+*),c",
        "10": "rrc (iy+*),d",
        "11": "rrc (iy+*),e",
        "12": "rrc (iy+*),h",
        "13": "rrc (iy+*),l",
        "14": "rrc (iy+*)",
        "15": "rrc (iy+*),a",
        "16": "rl (iy+*),b",
        "17": "rl (iy+*),c",
        "18": "rl (iy+*),d",
        "19": "rl (iy+*),e",
        "20": "rl (iy+*),h",
        "21": "rl (iy+*),l",
        "22": "rl (iy+*)",
        "23": "rl (iy+*),a",
        "24": "rr (iy+*),b",
        "25": "rr (iy+*),c",
        "26": "rr (iy+*),d",
        "27": "rr (iy+*),e",
        "28": "rr (iy+*),h",
        "29": "rr (iy+*),l",
        "30": "rr (iy+*)",
        "31": "rr (iy+*),a",
        "32": "sla (iy+*),b",
        "33": "sla (iy+*),c",
        "34": "sla (iy+*),d",
        "35": "sla (iy+*),e",
        "36": "sla (iy+*),h",
        "37": "sla (iy+*),l",
        "38": "sla (iy+*)",
        "39": "sla (iy+*),a",
        "40": "sra (iy+*),b",
        "41": "sra (iy+*),c",
        "42": "sra (iy+*),d",
        "43": "sra (iy+*),e",
        "44": "sra (iy+*),h",
        "45": "sra (iy+*),l",
        "46": "sra (iy+*)",
        "47": "sra (iy+*),a",
        "48": "sll (iy+*),b",
        "49": "sll (iy+*),c",
        "50": "sll (iy+*),d",
        "51": "sll (iy+*),e",
        "52": "sll (iy+*),h",
        "53": "sll (iy+*),l",
        "54": "sll (iy+*)",
        "55": "sll (iy+*),a",
        "56": "srl (iy+*),b",
        "57": "srl (iy+*),c",
        "58": "srl (iy+*),d",
        "59": "srl (iy+*),e",
        "60": "srl (iy+*),h",
        "61": "srl (iy+*),l",
        "62": "srl (iy+*)",
        "63": "srl (iy+*),a",
        "64": "bit 0,(iy+*)",
        "65": "bit 0,(iy+*)",
        "66": "bit 0,(iy+*)",
        "67": "bit 0,(iy+*)",
        "68": "bit 0,(iy+*)",
        "69": "bit 0,(iy+*)",
        "70": "bit 0,(iy+*)",
        "71": "bit 0,(iy+*)",
        "72": "bit 1,(iy+*)",
        "73": "bit 1,(iy+*)",
        "74": "bit 1,(iy+*)",
        "75": "bit 1,(iy+*)",
        "76": "bit 1,(iy+*)",
        "77": "bit 1,(iy+*)",
        "78": "bit 1,(iy+*)",
        "79": "bit 1,(iy+*)",
        "80": "bit 2,(iy+*)",
        "81": "bit 2,(iy+*)",
        "82": "bit 2,(iy+*)",
        "83": "bit 2,(iy+*)",
        "84": "bit 2,(iy+*)",
        "85": "bit 2,(iy+*)",
        "86": "bit 2,(iy+*)",
        "87": "bit 2,(iy+*)",
        "88": "bit 3,(iy+*)",
        "89": "bit 3,(iy+*)",
        "90": "bit 3,(iy+*)",
        "91": "bit 3,(iy+*)",
        "92": "bit 3,(iy+*)",
        "93": "bit 3,(iy+*)",
        "94": "bit 3,(iy+*)",
        "95": "bit 3,(iy+*)",
        "96": "bit 4,(iy+*)",
        "97": "bit 4,(iy+*)",
        "98": "bit 4,(iy+*)",
        "99": "bit 4,(iy+*)",
        "100": "bit 4,(iy+*)",
        "101": "bit 4,(iy+*)",
        "102": "bit 4,(iy+*)",
        "103": "bit 4,(iy+*)",
        "104": "bit 5,(iy+*)",
        "105": "bit 5,(iy+*)",
        "106": "bit 5,(iy+*)",
        "107": "bit 5,(iy+*)",
        "108": "bit 5,(iy+*)",
        "109": "bit 5,(iy+*)",
        "110": "bit 5,(iy+*)",
        "111": "bit 5,(iy+*)",
        "112": "bit 6,(iy+*)",
        "113": "bit 6,(iy+*)",
        "114": "bit 6,(iy+*)",
        "115": "bit 6,(iy+*)",
        "116": "bit 6,(iy+*)",
        "117": "bit 6,(iy+*)",
        "118": "bit 6,(iy+*)",
        "119": "bit 6,(iy+*)",
        "120": "bit 7,(iy+*)",
        "121": "bit 7,(iy+*)",
        "122": "bit 7,(iy+*)",
        "123": "bit 7,(iy+*)",
        "124": "bit 7,(iy+*)",
        "125": "bit 7,(iy+*)",
        "126": "bit 7,(iy+*)",
        "127": "bit 7,(iy+*)",
        "128": "res 0,(iy+*),b",
        "129": "res 0,(iy+*),c",
        "130": "res 0,(iy+*),d",
        "131": "res 0,(iy+*),e",
        "132": "res 0,(iy+*),h",
        "133": "res 0,(iy+*),l",
        "134": "res 0,(iy+*)",
        "135": "res 0,(iy+*),a",
        "136": "res 1,(iy+*),b",
        "137": "res 1,(iy+*),c",
        "138": "res 1,(iy+*),d",
        "139": "res 1,(iy+*),e",
        "140": "res 1,(iy+*),h",
        "141": "res 1,(iy+*),l",
        "142": "res 1,(iy+*)",
        "143": "res 1,(iy+*),a",
        "144": "res 2,(iy+*),b",
        "145": "res 2,(iy+*),c",
        "146": "res 2,(iy+*),d",
        "147": "res 2,(iy+*),e",
        "148": "res 2,(iy+*),h",
        "149": "res 2,(iy+*),l",
        "150": "res 2,(iy+*)",
        "151": "res 2,(iy+*),a",
        "152": "res 3,(iy+*),b",
        "153": "res 3,(iy+*),c",
        "154": "res 3,(iy+*),d",
        "155": "res 3,(iy+*),e",
        "156": "res 3,(iy+*),h",
        "157": "res 3,(iy+*),l",
        "158": "res 3,(iy+*)",
        "159": "res 3,(iy+*),a",
        "160": "res 4,(iy+*),b",
        "161": "res 4,(iy+*),c",
        "162": "res 4,(iy+*),d",
        "163": "res 4,(iy+*),e",
        "164": "res 4,(iy+*),h",
        "165": "res 4,(iy+*),l",
        "166": "res 4,(iy+*)",
        "167": "res 4,(iy+*),a",
        "168": "res 5,(iy+*),b",
        "169": "res 5,(iy+*),c",
        "170": "res 5,(iy+*),d",
        "171": "res 5,(iy+*),e",
        "172": "res 5,(iy+*),h",
        "173": "res 5,(iy+*),l",
        "174": "res 5,(iy+*)",
        "175": "res 5,(iy+*),a",
        "176": "res 6,(iy+*),b",
        "177": "res 6,(iy+*),c",
        "178": "res 6,(iy+*),d",
        "179": "res 6,(iy+*),e",
        "180": "res 6,(iy+*),h",
        "181": "res 6,(iy+*),l",
        "182": "res 6,(iy+*)",
        "183": "res 6,(iy+*),a",
        "184": "res 7,(iy+*),b",
        "185": "res 7,(iy+*),c",
        "186": "res 7,(iy+*),d",
        "187": "res 7,(iy+*),e",
        "188": "res 7,(iy+*),h",
        "189": "res 7,(iy+*),l",
        "190": "res 7,(iy+*)",
        "191": "res 7,(iy+*),a",
        "192": "set 0,(iy+*),b",
        "193": "set 0,(iy+*),c",
        "194": "set 0,(iy+*),d",
        "195": "set 0,(iy+*),e",
        "196": "set 0,(iy+*),h",
        "197": "set 0,(iy+*),l",
        "198": "set 0,(iy+*)",
        "199": "set 0,(iy+*),a",
        "200": "set 1,(iy+*),b",
        "201": "set 1,(iy+*),c",
        "202": "set 1,(iy+*),d",
        "203": "set 1,(iy+*),e",
        "204": "set 1,(iy+*),h",
        "205": "set 1,(iy+*),l",
        "206": "set 1,(iy+*)",
        "207": "set 1,(iy+*),a",
        "208": "set 2,(iy+*),b",
        "209": "set 2,(iy+*),c",
        "210": "set 2,(iy+*),d",
        "211": "set 2,(iy+*),e",
        "212": "set 2,(iy+*),h",
        "213": "set 2,(iy+*),l",
        "214": "set 2,(iy+*)",
        "215": "set 2,(iy+*),a",
        "216": "set 3,(iy+*),b",
        "217": "set 3,(iy+*),c",
        "218": "set 3,(iy+*),d",
        "219": "set 3,(iy+*),e",
        "220": "set 3,(iy+*),h",
        "221": "set 3,(iy+*),l",
        "222": "set 3,(iy+*)",
        "223": "set 3,(iy+*),a",
        "224": "set 4,(iy+*),b",
        "225": "set 4,(iy+*),c",
        "226": "set 4,(iy+*),d",
        "227": "set 4,(iy+*),e",
        "228": "set 4,(iy+*),h",
        "229": "set 4,(iy+*),l",
        "230": "set 4,(iy+*)",
        "231": "set 4,(iy+*),a",
        "232": "set 5,(iy+*),b",
        "233": "set 5,(iy+*),c",
        "234": "set 5,(iy+*),d",
        "235": "set 5,(iy+*),e",
        "236": "set 5,(iy+*),h",
        "237": "set 5,(iy+*),l",
        "238": "set 5,(iy+*)",
        "239": "set 5,(iy+*),a",
        "240": "set 6,(iy+*),b",
        "241": "set 6,(iy+*),c",
        "242": "set 6,(iy+*),d",
        "243": "set 6,(iy+*),e",
        "244": "set 6,(iy+*),h",
        "245": "set 6,(iy+*),l",
        "246": "set 6,(iy+*)",
        "247": "set 6,(iy+*),a",
        "248": "set 7,(iy+*),b",
        "249": "set 7,(iy+*),c",
        "250": "set 7,(iy+*),d",
        "251": "set 7,(iy+*),e",
        "252": "set 7,(iy+*),h",
        "253": "set 7,(iy+*),l",
        "254": "set 7,(iy+*)",
        "255": "set 7,(iy+*),a"
      }
    },
    "ED": {
      "SubTables": {},
      "Opcodes": {
        "64": "in b,(c)",
        "65": "out (c),b",
        "66": "sbc hl,bc",
        "67": "ld (**),bc",
        "68": "neg",
        "69": "retn",
        "70": "im 0",
        "71": "ld i,a",
        "72": "in c,(c)",
        "73": "out (c),c",
        "74": "adc hl,bc",
        "75": "ld bc,(**)",
        "76": "neg",
        "77": "reti",
        "78": "im 0/1",
        "79": "ld r,a",
        "80": "in d,(c)",
        "81": "out (c),d",
        "82": "sbc hl,de",
        "83": "ld (**),de",
        "84": "neg",
        "85": "retn",
        "86": "im 1",
        "87": "ld a,i",
        "88": "in e,(c)",
        "89": "out (c),e",
        "90": "adc hl,de",
        "91": "ld de,(**)",
        "92": "neg",
        "93": "retn",
        "94": "im 2",
        "95": "ld a,r",
        "96": "in h,(c)",
        "97": "out (c),h",
        "98": "sbc hl,hl",
        "99": "ld (**),hl",
        "100": "neg",
        "101": "retn",
        "102": "im 0",
        "103": "rrd",
        "104": "in l,(c)",
        "105": "out (c),l",
        "106": "adc hl,hl",
        "107": "ld hl,(**)",
        "108": "neg",
        "109": "retn",
        "110": "im 0/1",
        "111": "rld",
        "112": "in (c)",
        "113": "out (c),0",
        "114": "sbc hl,sp",
        "115": "ld (**),sp",
        "116": "neg",
        "117": "retn",
        "118": "im 1",
        "120": "in a,(c)",
        "121": "out (c),a",
        "122": "adc hl,sp",
        "123": "ld sp,(**)",
        "124": "neg",
        "125": "retn",
        "126": "im 2",
        "160": "ldi",
        "161": "cpi",
        "162": "ini",
        "163": "outi",
        "168": "ldd",
        "169": "cpd",
        "170": "ind",
        "171": "outd",
        "176": "ldir",
        "177": "cpir",
        "178": "inir",
        "179": "otir",
        "184": "lddr",
        "185": "cpdr",
        "186": "indr",
        "187": "otdr"
      }
    }
  }
}